blockedaicrawlers/__init__.py
blockedaicrawlers/ai_crawlers.json
blockedaicrawlers/blocker.py
blockaicrawlers-0.1.0.dist-info/METADATA
blockaicrawlers-0.1.0.dist-info/WHEEL
blockaicrawlers-0.1.0.dist-info/top_level.txt
blockaicrawlers-0.1.0.dist-info/RECORD
