Metadata-Version: 2.4
Name: blockaicrawlers
Version: 0.1.0
Summary: A Flask extension to detect and block AI crawlers based on User-Agent headers.
Author-email: Shreyan Basu Ray <basurayshreyan@gmail.com>
License: MIT
Project-URL: Homepage, https://github.com/Shreyan1/Block-AICrawlers
Requires-Python: >=3.9
Requires-Dist: flask>=2.0
Requires-Dist: flask-limiter>=3.0
Provides-Extra: dev
Requires-Dist: pytest; extra == "dev"
Requires-Dist: rich; extra == "dev"
